notebooklm_mcp/__init__.py
notebooklm_mcp/cli.py
notebooklm_mcp/client.py
notebooklm_mcp/config.py
notebooklm_mcp/exceptions.py
notebooklm_mcp/monitoring.py
notebooklm_mcp/py.typed
notebooklm_mcp/server.py
notebooklm_mcp-2.0.11.dist-info/licenses/LICENSE
notebooklm_mcp-2.0.11.dist-info/METADATA
notebooklm_mcp-2.0.11.dist-info/WHEEL
notebooklm_mcp-2.0.11.dist-info/entry_points.txt
notebooklm_mcp-2.0.11.dist-info/top_level.txt
notebooklm_mcp-2.0.11.dist-info/RECORD
