Metadata-Version: 2.4
Name: notebooklm-mcp
Version: 2.0.11
Summary: FastMCP v2 server for NotebookLM automation with modern async support
Author-email: NotebookLM MCP Team <support@notebooklm-mcp.dev>
Maintainer-email: NotebookLM MCP Team <support@notebooklm-mcp.dev>
License-Expression: MIT
Project-URL: Homepage, https://github.com/notebooklm-mcp/notebooklm-mcp
Project-URL: Documentation, https://notebooklm-mcp.readthedocs.io
Project-URL: Repository, https://github.com/notebooklm-mcp/notebooklm-mcp
Project-URL: Issues, https://github.com/notebooklm-mcp/notebooklm-mcp/issues
Project-URL: Changelog, https://github.com/notebooklm-mcp/notebooklm-mcp/blob/main/CHANGELOG.md
Keywords: fastmcp,mcp,notebooklm,automation,ai,llm,fastmcp-v2
Classifier: Development Status :: 5 - Production/Stable
Classifier: Intended Audience :: Developers
Classifier: Operating System :: OS Independent
Classifier: Programming Language :: Python :: 3
Classifier: Programming Language :: Python :: 3.10
Classifier: Programming Language :: Python :: 3.11
Classifier: Programming Language :: Python :: 3.12
Classifier: Topic :: Software Development :: Libraries :: Python Modules
Classifier: Topic :: Internet :: WWW/HTTP :: Browsers
Classifier: Topic :: Scientific/Engineering :: Artificial Intelligence
Requires-Python: >=3.10
License-File: LICENSE
Requires-Dist: fastmcp>=2.0.0
Requires-Dist: selenium>=4.22.0
Requires-Dist: undetected-chromedriver>=3.5.4
Requires-Dist: anyio>=4.4.0
Requires-Dist: trio>=0.26.0
Requires-Dist: async-timeout>=4.0.3
Requires-Dist: pydantic>=2.8.2
Requires-Dist: click>=8.0.0
Requires-Dist: rich>=13.0.0
Requires-Dist: loguru>=0.7.2
Requires-Dist: typing-extensions>=4.0.0
Requires-Dist: psutil>=5.9.0
Requires-Dist: tomli>=2.0.0; python_version < "3.11"
Dynamic: license-file
